{
  "frames": {
    "000_43.png": {
      "frame": {
        "x": 0,
        "y": 0,
        "w": 141,
        "h": 62
      },
      "rotated": false,
      "trimmed": false,
      "spriteSourceSize": {
        "x": 0,
        "y": 0,
        "w": 141,
        "h": 62
      },
      "sourceSize": {
        "w": 141,
        "h": 62
      },
      "anchor": {
        "x": 0.49645390070921985,
        "y": 0.8548387096774194
      }
    },
    "001_43.png": {
      "frame": {
        "x": 142,
        "y": 0,
        "w": 195,
        "h": 78
      },
      "rotated": false,
      "trimmed": false,
      "spriteSourceSize": {
        "x": 0,
        "y": 0,
        "w": 195,
        "h": 78
      },
      "sourceSize": {
        "w": 195,
        "h": 78
      },
      "anchor": {
        "x": 0.5025641025641026,
        "y": 0.48717948717948717
      }
    }
  },
  "meta": {
    "app": "pack_aoe1_atlases.py",
    "version": "1.0.0",
    "image": "texture.png",
    "format": "RGBA8888",
    "size": {
      "w": 337,
      "h": 78
    },
    "scale": 1
  }
}