{
  "frames": {
    "000_466.png": {
      "frame": {
        "x": 0,
        "y": 0,
        "w": 59,
        "h": 64
      },
      "rotated": false,
      "trimmed": false,
      "spriteSourceSize": {
        "x": 0,
        "y": 0,
        "w": 59,
        "h": 64
      },
      "sourceSize": {
        "w": 59,
        "h": 64
      },
      "anchor": {
        "x": 0.3898305084745763,
        "y": 0.765625
      }
    }
  },
  "meta": {
    "app": "pack_aoe1_atlases.py",
    "version": "1.0.0",
    "image": "texture.png",
    "format": "RGBA8888",
    "size": {
      "w": 59,
      "h": 64
    },
    "scale": 1
  }
}